openpyxl_dictreader.py
openpyxl_dictreader-0.1.8.dist-info/LICENSE
openpyxl_dictreader-0.1.8.dist-info/METADATA
openpyxl_dictreader-0.1.8.dist-info/WHEEL
openpyxl_dictreader-0.1.8.dist-info/top_level.txt
openpyxl_dictreader-0.1.8.dist-info/RECORD
