Metadata-Version: 2.1
Name: openpyxl-dictreader
Version: 0.1.8
Summary: A simple package to read openpyxl worksheets like a csv DictReader
Home-page: https://github.com/foprel/openpyxl-dictreader
Author: Frank Oprel
Author-email: oprel.fj@gmail.com
License: UNKNOWN
Platform: UNKNOWN
License-File: LICENSE
Requires-Dist: openpyxl (~=3.0.3)
